viz_media_in_html/__init__.py
viz_media_in_html/__main__.py
viz_media_in_html/cli.py
viz_media_in_html/core.py
viz_media_in_html/html.py
viz_media_in_html/server.py
viz_media_in_html-1.0.0.dist-info/licenses/LICENSE
viz_media_in_html-1.0.0.dist-info/METADATA
viz_media_in_html-1.0.0.dist-info/WHEEL
viz_media_in_html-1.0.0.dist-info/entry_points.txt
viz_media_in_html-1.0.0.dist-info/top_level.txt
viz_media_in_html-1.0.0.dist-info/RECORD
