Metadata-Version: 2.4
Name: viz-media-in-html
Version: 1.0.0
Summary: 在浏览器中可视化浏览本地图片/视频：分类、搜索、分页、Lightbox，内置本地 HTTP 服务且不在页面/日志中暴露真实路径
Author: dreamer
License-Expression: MIT
Keywords: html,visualization,image,video,http
Classifier: Programming Language :: Python :: 3
Classifier: Operating System :: OS Independent
Classifier: Environment :: Console
Classifier: Topic :: Multimedia
Classifier: Topic :: Internet :: WWW/HTTP :: HTTP Servers
Requires-Python: >=3.8
License-File: LICENSE
Dynamic: license-file
